{
  "mcpServers": {
    "tableau": {
      "command": "node",
      "args": ["build/index.js"],
      "env": {
        "SERVER": "https://my-tableau-server.com",
        "DATASOURCE_LUID": "",
        "SITE_NAME": "",
        "PAT_NAME": "",
        "PAT_VALUE": "",
        "JWT": "",
        "USERNAME": "",
        "PASSWORD": "",
        "CONNECTED_APP_CLIENT_ID": "",
        "CONNECTED_APP_SECRET_ID": "",
        "CONNECTED_APP_SECRET_VALUE": "",
        "JWT_SCOPES": "",
        "AUTH_TYPE": "",
        "DEFAULT_LOG_LEVEL": "debug"
      }
    }
  }
}
